deltaman/__init__.py
deltaman/_lark_parser.py
deltaman/delta.lark
deltaman/delta_parser.py
deltaman-0.0.4.dist-info/LICENSE
deltaman-0.0.4.dist-info/WHEEL
deltaman-0.0.4.dist-info/METADATA
deltaman-0.0.4.dist-info/RECORD
