Metadata-Version: 2.1
Name: deltaman
Version: 0.0.4
Summary: Parsing human time intervals
Home-page: https://github.com/wonderbeyond/deltaman
License: MIT
Keywords: python,datetime,timedelta,human,interval
Author: Wonder
Author-email: wonderbeyond@gmail.com
Requires-Python: >=3.7,<4.0
Classifier: Intended Audience :: Developers
Classifier: License :: OSI Approved :: MIT License
Classifier: Operating System :: OS Independent
Classifier: Programming Language :: Python :: 3
Classifier: Programming Language :: Python :: 3.7
Classifier: Programming Language :: Python :: 3.8
Classifier: Topic :: Software Development :: Libraries :: Python Modules
Provides-Extra: building
Provides-Extra: testing
Requires-Dist: lark (>=1.1.2,<2.0.0); extra == "building"
Requires-Dist: pytest (>=7.1.2,<8.0.0); extra == "testing"
Requires-Dist: tox (>=3.25.0,<4.0.0); extra == "testing"
Project-URL: Documentation, https://github.com/wonderbeyond/deltaman
Project-URL: Repository, https://github.com/wonderbeyond/deltaman
